sql2code/__init__.py
sql2code/core.py
sql2code/sql2dart.py
sql2code-0.0.2.dist-info/entry_points.txt
sql2code-0.0.2.dist-info/LICENSE
sql2code-0.0.2.dist-info/WHEEL
sql2code-0.0.2.dist-info/METADATA
sql2code-0.0.2.dist-info/RECORD
