Metadata-Version: 2.1
Name: sql2code
Version: 0.0.2
Summary: Convert SQL to import-able code!
Home-page: http://github.com/scientifichackers/sql2code
License: UNKNOWN
Author: Dev Aggarwal
Author-email: devxpy@gmail.com
Requires-Python: >=3.6
Classifier: License :: OSI Approved :: MIT License
Requires-Dist: sly
Requires-Dist: click
